gitted/__init__.py
gitted/diff2msg.py
gitted-0.0.19.data/scripts/branch
gitted-0.0.19.data/scripts/commit
gitted-0.0.19.data/scripts/pull
gitted-0.0.19.data/scripts/push
gitted-0.0.19.dist-info/licenses/LICENSE.txt
gitted-0.0.19.dist-info/METADATA
gitted-0.0.19.dist-info/WHEEL
gitted-0.0.19.dist-info/top_level.txt
gitted-0.0.19.dist-info/RECORD
