Metadata-Version: 2.4
Name: gitted
Version: 0.0.19
Summary: Collection of Bash scripts for Git auto-piloting, such as branch, push, pull, and commit.
Author-email: Yegor Bugayenko <yegor256@gmail.com>
License: MIT
Project-URL: Homepage, https://github.com/yegor256/gitted
Classifier: Development Status :: 3 - Alpha
Classifier: Intended Audience :: Developers
Classifier: Topic :: Software Development :: Version Control :: Git
Classifier: License :: OSI Approved :: MIT License
Classifier: Programming Language :: Python :: 3
Classifier: Programming Language :: Python :: 3.6
Classifier: Programming Language :: Python :: 3.7
Classifier: Programming Language :: Python :: 3.8
Classifier: Programming Language :: Python :: 3.9
Classifier: Programming Language :: Python :: 3.10
Requires-Python: >=3.9
License-File: LICENSE.txt
Requires-Dist: openai>=1.82.0
Dynamic: license-file
